figural/pentagonal.py
figural/triangular.py
figural-0.1.0.dist-info/METADATA
figural-0.1.0.dist-info/WHEEL
figural-0.1.0.dist-info/RECORD
