Metadata-Version: 2.4
Name: figural
Version: 0.1.0
Summary: A tiny Python library for generating, testing and ploting triangular and pentagonal numbers
Project-URL: Homepage, https://github.com/twaclaw/figural
Project-URL: Documentation, https://github.com/twaclaw/figural
Project-URL: Issues, https://github.com/twaclaw/figural/issues
Author-email: Diego Sandoval <dsandovalv@gmail.com>
Maintainer-email: Diego Sandoval <dsandovalv@gmail.com>
Keywords: figural,numpy,pentagonal numbers,triangular numbers
Classifier: Development Status :: 4 - Beta
Classifier: Intended Audience :: Developers
Classifier: Intended Audience :: Education
Classifier: Intended Audience :: Science/Research
Classifier: License :: OSI Approved :: MIT License
Classifier: Operating System :: POSIX
Classifier: Operating System :: Unix
Classifier: Programming Language :: Python
Classifier: Programming Language :: Python :: 3
Classifier: Programming Language :: Python :: 3.11
Classifier: Programming Language :: Python :: 3.12
Classifier: Programming Language :: Python :: 3.13
Classifier: Programming Language :: Python :: 3.14
Classifier: Topic :: Scientific/Engineering
Requires-Python: >=3.11
Requires-Dist: matplotlib>=3.10.7
Requires-Dist: numpy>=2.3.5
Requires-Dist: tikzplotlib>=0.10.1
Provides-Extra: dev
Requires-Dist: hatch; extra == 'dev'
Requires-Dist: pre-commit; extra == 'dev'
Requires-Dist: ruff; extra == 'dev'
